subnoto_api_client/__init__.py
subnoto_api_client/client.py
subnoto_api_client/generated/__init__.py
subnoto_api_client/generated/api/__init__.py
subnoto_api_client/generated/api/contact/__init__.py
subnoto_api_client/generated/api/contact/post_public_contact_create.py
subnoto_api_client/generated/api/contact/post_public_contact_delete.py
subnoto_api_client/generated/api/contact/post_public_contact_get.py
subnoto_api_client/generated/api/contact/post_public_contact_list.py
subnoto_api_client/generated/api/contact/post_public_contact_update.py
subnoto_api_client/generated/api/envelope/__init__.py
subnoto_api_client/generated/api/envelope/post_public_envelope_add_attachment.py
subnoto_api_client/generated/api/envelope/post_public_envelope_add_blocks.py
subnoto_api_client/generated/api/envelope/post_public_envelope_add_recipients.py
subnoto_api_client/generated/api/envelope/post_public_envelope_create_from_file.py
subnoto_api_client/generated/api/envelope/post_public_envelope_create_from_template.py
subnoto_api_client/generated/api/envelope/post_public_envelope_delete.py
subnoto_api_client/generated/api/envelope/post_public_envelope_delete_attachment.py
subnoto_api_client/generated/api/envelope/post_public_envelope_delete_blocks.py
subnoto_api_client/generated/api/envelope/post_public_envelope_delete_recipients.py
subnoto_api_client/generated/api/envelope/post_public_envelope_get.py
subnoto_api_client/generated/api/envelope/post_public_envelope_get_document.py
subnoto_api_client/generated/api/envelope/post_public_envelope_get_proof.py
subnoto_api_client/generated/api/envelope/post_public_envelope_list.py
subnoto_api_client/generated/api/envelope/post_public_envelope_send.py
subnoto_api_client/generated/api/envelope/post_public_envelope_sign.py
subnoto_api_client/generated/api/envelope/post_public_envelope_update.py
subnoto_api_client/generated/api/template/__init__.py
subnoto_api_client/generated/api/template/post_public_template_list.py
subnoto_api_client-2.3.10.dist-info/WHEEL
subnoto_api_client-2.3.10.dist-info/METADATA
subnoto_api_client-2.3.10.dist-info/RECORD
