Metadata-Version: 2.1
Name: subnoto-api-client
Author: Subnoto
Author-email: support@subnoto.com
Home-page: https://subnoto.com
License: Apache-2.0
Summary: Python client for the Subnoto Public API
Project-URL: Documentation, https://subnoto.com/documentation/developers/sdks/python
Project-URL: Homepage, https://subnoto.com
Project-URL: Repository, https://gitlab.com/subnoto/subnoto-monorepo-public
Classifier: Development Status :: 5 - Production/Stable
Classifier: Intended Audience :: Developers
Classifier: License :: OSI Approved :: Apache Software License
Classifier: Programming Language :: Python :: 3
Classifier: Programming Language :: Python :: 3.8
Classifier: Programming Language :: Python :: 3.9
Classifier: Programming Language :: Python :: 3.10
Classifier: Programming Language :: Python :: 3.11
Classifier: Programming Language :: Python :: 3.12
Classifier: Topic :: Software Development :: Libraries :: Python Modules
Classifier: Topic :: Internet :: WWW/HTTP :: HTTP Servers
Requires-Python: >=3.8
Requires-Dist: httpx
Requires-Dist: attrs
Requires-Dist: http-message-signatures
Version: 2.3.10
